{
    "key": "group_68ee929470223",
    "title": "Defaults",
    "fields": [
        {
            "key": "field_68ee9294712a7",
            "label": "Article Cards",
            "name": "article_cards",
            "aria-label": "",
            "type": "group",
            "instructions": "",
            "required": 0,
            "conditional_logic": 0,
            "wrapper": {
                "width": "",
                "class": "",
                "id": ""
            },
            "layout": "block",
            "sub_fields": [
                {
                    "key": "field_68ee9294712ab",
                    "label": "Headline",
                    "name": "headline",
                    "aria-label": "",
                    "type": "text",
                    "instructions": "If left blank, the default headline will be used. The default can be customized under <a href=\"\/wp-admin\/admin.php?page=acf-options-theme-options\">Theme Options<\/a> > Defaults > Article Cards Headline",
                    "required": 0,
                    "conditional_logic": 0,
                    "wrapper": {
                        "width": "",
                        "class": "",
                        "id": ""
                    },
                    "default_value": "",
                    "maxlength": "",
                    "allow_in_bindings": 1,
                    "placeholder": "",
                    "prepend": "",
                    "append": ""
                },
                {
                    "key": "field_68ee9294712b1",
                    "label": "Button",
                    "name": "button",
                    "aria-label": "",
                    "type": "link",
                    "instructions": "If left blank, the default button text will be used. The default can be customized under <a href=\"\/wp-admin\/admin.php?page=acf-options-theme-options\">Theme Options<\/a> > Defaults > Article Cards Button Text",
                    "required": 0,
                    "conditional_logic": 0,
                    "wrapper": {
                        "width": "",
                        "class": "",
                        "id": ""
                    },
                    "return_format": "array",
                    "allow_in_bindings": 0
                },
                {
                    "key": "field_68ee9294712b4",
                    "label": "Post Selection",
                    "name": "display",
                    "aria-label": "",
                    "type": "radio",
                    "instructions": "",
                    "required": 0,
                    "conditional_logic": 0,
                    "wrapper": {
                        "width": "",
                        "class": "",
                        "id": ""
                    },
                    "choices": {
                        "recent": "Most Recent",
                        "category": "By Category",
                        "post_tag": "By Tag",
                        "custom": "Custom Selection"
                    },
                    "default_value": "",
                    "return_format": "value",
                    "allow_null": 0,
                    "other_choice": 0,
                    "allow_in_bindings": 1,
                    "layout": "vertical",
                    "save_other_choice": 0
                },
                {
                    "key": "field_68ee9294712b7",
                    "label": "Post Category",
                    "name": "category",
                    "aria-label": "",
                    "type": "taxonomy",
                    "instructions": "",
                    "required": 1,
                    "conditional_logic": [
                        [
                            {
                                "field": "field_68ee9294712b4",
                                "operator": "==",
                                "value": "category"
                            }
                        ]
                    ],
                    "wrapper": {
                        "width": "",
                        "class": "",
                        "id": ""
                    },
                    "taxonomy": "category",
                    "add_term": 0,
                    "save_terms": 0,
                    "load_terms": 0,
                    "return_format": "id",
                    "field_type": "select",
                    "allow_null": 0,
                    "bidirectional": 0,
                    "multiple": 0,
                    "bidirectional_target": []
                },
                {
                    "key": "field_68ee9294712bb",
                    "label": "Post Tag",
                    "name": "post_tag",
                    "aria-label": "",
                    "type": "taxonomy",
                    "instructions": "",
                    "required": 1,
                    "conditional_logic": [
                        [
                            {
                                "field": "field_68ee9294712b4",
                                "operator": "==",
                                "value": "post_tag"
                            }
                        ]
                    ],
                    "wrapper": {
                        "width": "",
                        "class": "",
                        "id": ""
                    },
                    "taxonomy": "post_tag",
                    "add_term": 0,
                    "save_terms": 0,
                    "load_terms": 0,
                    "return_format": "id",
                    "field_type": "select",
                    "allow_null": 0,
                    "bidirectional": 0,
                    "multiple": 0,
                    "bidirectional_target": []
                },
                {
                    "key": "field_68ee9294712be",
                    "label": "Custom Selection",
                    "name": "custom",
                    "aria-label": "",
                    "type": "relationship",
                    "instructions": "",
                    "required": 1,
                    "conditional_logic": [
                        [
                            {
                                "field": "field_68ee9294712b4",
                                "operator": "==",
                                "value": "custom"
                            }
                        ]
                    ],
                    "wrapper": {
                        "width": "",
                        "class": "",
                        "id": ""
                    },
                    "post_type": [
                        "post"
                    ],
                    "post_status": "",
                    "taxonomy": "",
                    "filters": [
                        "search"
                    ],
                    "return_format": "id",
                    "min": 3,
                    "max": 3,
                    "allow_in_bindings": 1,
                    "elements": "",
                    "bidirectional": 0,
                    "bidirectional_target": []
                }
            ]
        }
    ],
    "location": [
        [
            {
                "param": "options_page",
                "operator": "==",
                "value": "acf-options-theme-options"
            }
        ]
    ],
    "menu_order": 4,
    "position": "normal",
    "style": "default",
    "label_placement": "top",
    "instruction_placement": "label",
    "hide_on_screen": "",
    "active": true,
    "description": "",
    "show_in_rest": 0,
    "display_title": "",
    "modified": 1760465915
}
